cli.py
run_get_stock_news.py
GetStockNews/__init__.py
GetStockNews/runner.py
GetStockNews/scraper.py
GetStockNews/symbols.py
stock_newscraper-0.4.0.dist-info/licenses/LICENSE
stock_newscraper-0.4.0.dist-info/METADATA
stock_newscraper-0.4.0.dist-info/WHEEL
stock_newscraper-0.4.0.dist-info/entry_points.txt
stock_newscraper-0.4.0.dist-info/top_level.txt
stock_newscraper-0.4.0.dist-info/RECORD
