Metadata-Version: 2.4
Name: stock-newscraper
Version: 0.4.0
Summary: Collect Google News articles for Taiwanese stocks and keywords.
Author: Hung-Ching Lee
License-Expression: MIT
Project-URL: Homepage, https://github.com/abin-trading/Arbitbot
Project-URL: Source, https://github.com/abin-trading/Arbitbot
Project-URL: Documentation, https://github.com/abin-trading/Arbitbot#readme
Keywords: news,google-news,stock,playwright,taiwan,scraping
Classifier: Development Status :: 4 - Beta
Classifier: Intended Audience :: Developers
Classifier: Topic :: Internet :: WWW/HTTP :: Dynamic Content
Classifier: Programming Language :: Python :: 3
Classifier: Programming Language :: Python :: 3.10
Classifier: Programming Language :: Python :: 3.11
Classifier: Programming Language :: Python :: 3.12
Requires-Python: >=3.10
License-File: LICENSE
Requires-Dist: feedparser>=6.0.10
Requires-Dist: pygooglenews>=0.5.1
Requires-Dist: requests>=2.31.0
Requires-Dist: beautifulsoup4>=4.12.0
Requires-Dist: playwright>=1.44.0
Requires-Dist: dateparser>=1.1.3
Requires-Dist: pandas>=2.0.0
Requires-Dist: pyarrow>=9.0.0
Dynamic: license-file
